openpix/__init__.py
openpix_sdk-0.1.0.dist-info/licenses/LICENSE
openpix_sdk-0.1.0.dist-info/METADATA
openpix_sdk-0.1.0.dist-info/WHEEL
openpix_sdk-0.1.0.dist-info/top_level.txt
openpix_sdk-0.1.0.dist-info/RECORD
