Metadata-Version: 2.4
Name: openpix-sdk
Version: 0.1.0
Summary: Async OpenPix SDK
Author-email: Fabio Antonio Astore <astore.a.fabio@gmail.com>
License: MIT License
Requires-Python: >=3.13.3
License-File: LICENSE
Requires-Dist: httpx==0.28.1
Requires-Dist: ijson==3.4.0
Requires-Dist: pydantic==2.11.5
Requires-Dist: pydantic-extra-types==2.10.4
Requires-Dist: phonenumbers==9.0.5
Requires-Dist: email_validator==2.2.0
Requires-Dist: pydantic-br==1.1.0
Dynamic: license-file
